yugioh_scraper/__init__.py
yugioh_scraper/items.py
yugioh_scraper/middlewares.py
yugioh_scraper/pipelines.py
yugioh_scraper/settings.py
yugioh_scraper/spiders/__init__.py
yugioh_scraper/spiders/db_yugioh_card.py
yugioh_scraper-0.2.0.dist-info/LICENSE.md
yugioh_scraper-0.2.0.dist-info/METADATA
yugioh_scraper-0.2.0.dist-info/WHEEL
yugioh_scraper-0.2.0.dist-info/entry_points.txt
yugioh_scraper-0.2.0.dist-info/top_level.txt
yugioh_scraper-0.2.0.dist-info/RECORD
