Metadata-Version: 2.1
Name: yugioh-scraper
Version: 0.2.0
Summary: Yu-Gi-Oh! Scraper is a project that crawls websites and APIs and extracts Yu-Gi-Oh! related data from their pages.
Author-email: Albert Marrero <contact@albertmarrero.me>
Maintainer-email: Albert Marrero <contact@albertmarrero.me>
License: 
Project-URL: Homepage, https://github.com/albert-marrero/Yu-Gi-Oh-Scraper/wiki
Project-URL: Bug Reports, https://github.com/albert-marrero/Yu-Gi-Oh-Scraper/issues
Project-URL: Source, https://github.com/albert-marrero/Yu-Gi-Oh-Scraper
Keywords: scraper,scrapy,yugioh,data,datasets
Classifier: Development Status :: 3 - Alpha
Classifier: License :: OSI Approved :: MIT License
Classifier: Programming Language :: Python :: 3
Classifier: Programming Language :: Python :: 3.11
Classifier: Programming Language :: Python :: 3 :: Only
Classifier: Framework :: Scrapy
Requires-Python: >=3.7
License-File: LICENSE.md
Requires-Dist: scrapy
